codeit/__init__.py
codeit/Photo/photo.py
codeir-0.1.dist-info/METADATA
codeir-0.1.dist-info/WHEEL
codeir-0.1.dist-info/top_level.txt
codeir-0.1.dist-info/RECORD
