Metadata-Version: 2.4
Name: codeir
Version: 0.1
Summary: check codeit.ir
Author-email: Codeit <Amir.z.nine.three@gmail.com>
License: MIT
Project-URL: Homepage, https://codeit.ir
Classifier: Programming Language :: Python :: 3
Classifier: License :: OSI Approved :: MIT License
Classifier: Operating System :: OS Independent
Requires-Python: >=3.10
